pfdl_scheduler/__init__.py
pfdl_scheduler/extension.py
pfdl_scheduler/scheduler.py
pfdl_scheduler/api/__init__.py
pfdl_scheduler/api/observer_api.py
pfdl_scheduler/api/service_api.py
pfdl_scheduler/api/task_api.py
pfdl_scheduler/model/__init__.py
pfdl_scheduler/model/array.py
pfdl_scheduler/model/condition.py
pfdl_scheduler/model/counting_loop.py
pfdl_scheduler/model/loop.py
pfdl_scheduler/model/parallel.py
pfdl_scheduler/model/process.py
pfdl_scheduler/model/service.py
pfdl_scheduler/model/struct.py
pfdl_scheduler/model/task.py
pfdl_scheduler/model/task_call.py
pfdl_scheduler/model/while_loop.py
pfdl_scheduler/parser/PFDLLexer.py
pfdl_scheduler/parser/PFDLParser.py
pfdl_scheduler/parser/PFDLParserVisitor.py
pfdl_scheduler/parser/__init__.py
pfdl_scheduler/parser/pfdl_tree_visitor.py
pfdl_scheduler/petri_net/__init__.py
pfdl_scheduler/petri_net/callbacks.py
pfdl_scheduler/petri_net/drawer.py
pfdl_scheduler/petri_net/generator.py
pfdl_scheduler/petri_net/logic.py
pfdl_scheduler/scheduling/__init__.py
pfdl_scheduler/scheduling/event.py
pfdl_scheduler/scheduling/task_callbacks.py
pfdl_scheduler/utils/__init__.py
pfdl_scheduler/utils/dashboard_observer.py
pfdl_scheduler/utils/helpers.py
pfdl_scheduler/utils/log_entry_observer.py
pfdl_scheduler/utils/parsing_utils.py
pfdl_scheduler/validation/__init__.py
pfdl_scheduler/validation/error_handler.py
pfdl_scheduler/validation/semantic_error_checker.py
pfdl_scheduler/validation/syntax_error_listener.py
tests/__init__.py
tests/integration_tests/__init__.py
tests/integration_tests/test_scheduling_callbacks.py
tests/integration_tests/test_scheduling_marking.py
tests/integration_tests/test_visitor.py
tests/unit_test/__init__.py
tests/unit_test/test_error_handler.py
tests/unit_test/test_helpers.py
tests/unit_test/test_pfdl_tree_visitor.py
tests/unit_test/test_scheduler.py
tests/unit_test/test_semantic_error_checker.py
tests/unit_test/model/__init__.py
tests/unit_test/model/test_array.py
tests/unit_test/model/test_condition.py
pfdl_scheduler-0.9.0.dist-info/LICENSE
pfdl_scheduler-0.9.0.dist-info/METADATA
pfdl_scheduler-0.9.0.dist-info/WHEEL
pfdl_scheduler-0.9.0.dist-info/top_level.txt
pfdl_scheduler-0.9.0.dist-info/RECORD
