Metadata-Version: 2.1
Name: pfdl_scheduler
Version: 0.9.0
Summary: Parser and Scheduler of Production Flow Description Language (PFDL) files.
Author: Peter Detzner, Maximilian Hoerstrup
Author-email: maximilian.hoerstrup@iml.fraunhofer.de
Classifier: License :: OSI Approved :: MIT License
Classifier: Programming Language :: Python :: 3 :: Only
Classifier: Operating System :: OS Independent
Requires-Python: >=3.10
License-File: LICENSE
Requires-Dist: antlr4-python3-runtime ==4.9.3
Requires-Dist: antlr-denter
Requires-Dist: snakes
Requires-Dist: requests
